README.rst
setup.py
datacoco_email_tools/__init__.py
datacoco_email_tools/__version__.py
datacoco_email_tools/email_tools.py
datacoco_email_tools.egg-info/PKG-INFO
datacoco_email_tools.egg-info/SOURCES.txt
datacoco_email_tools.egg-info/dependency_links.txt
datacoco_email_tools.egg-info/requires.txt
datacoco_email_tools.egg-info/top_level.txt